jpbuilder/__init__.py
jpbuilder/__main__.py
jpbuilder-0.1.3.dist-info/METADATA
jpbuilder-0.1.3.dist-info/WHEEL
jpbuilder-0.1.3.dist-info/top_level.txt
jpbuilder-0.1.3.dist-info/RECORD
